{
  "name": "portal_hub",
  "nbt": [
    {
      "tagType": 10,
      "name": "",
      "value": [
        {
          "tagType": 9,
          "name": "size",
          "value": {
            "tagListType": 3,
            "list": [
              23,
              15,
              23
            ]
          }
        },
        {
          "tagType": 9,
          "name": "entities",
          "value": {
            "tagListType": 0,
            "list": null
          }
        },
        {
          "tagType": 9,
          "name": "blocks",
          "value": {
            "tagListType": 10,
            "list": [
              [
                {
                  "tagType": 9,
                  "name": "pos",
                  "value": {
                    "tagListType": 3,
                    "list": [
                      5,
                      0,
                      13
                    ]
                  }
                },
                {
                  "tagType": 3,
                  "name": "state",
                  "value": 0
                }
              ],
              [
                {
                  "tagType": 9,
                  "name": "pos",
                  "value": {
                    "tagListType": 3,
                    "list": [
                      6,
                      0,
                      13
                    ]
                  }
                },
                {
                  "tagType": 3,
                  "name": "state",
                  "value": 0
                }
              ],
              [
                {
                  "tagType": 9,
                  "name": "pos",
                  "value": {
                    "tagListType": 3,
                    "list": [
                      7,
                      0,
                      13
                    ]
                  }
                },
                {
                  "tagType": 3,
                  "name": "state",
                  "value": 0
                }
              ],
              [
                {
                  "tagType": 9,
                  "name": "pos",
                  "value": {
                    "tagListType": 3,
                    "list": [
                      8,
                      0,
                      13
                    ]
                  }
                },
                {
                  "tagType": 3,
                  "name": "state",
                  "value": 0
                }
              ],
              [
                {
                  "tagType": 9,
                  "name": "pos",
                  "value": {
                    "tagListType": 3,
                    "list": [
                      9,
                      0,
                      13
                    ]
                  }
                },
                {
                  "tagType": 3,
                  "name": "state",
                  "value": 0
                }
              ],
              [
                {
                  "tagType": 9,
                  "name": "pos",
                  "value": {
                    "tagListType": 3,
                    "list": [
                      10,
                      0,
                      13
                    ]
                  }
                },
                {
                  "tagType": 3,
                  "name": "state",
                  "value": 0
                }
              ],
              [
                {
                  "tagType": 9,
                  "name": "pos",
                  "value": {
                    "tagListType": 3,
                    "list": [
                      5,
                      1,
                      13
                    ]
                  }
                },
                {
                  "tagType": 3,
                  "name": "state",
                  "value": 0
                }
              ],
              [
                {
                  "tagType": 9,
                  "name": "pos",
                  "value": {
                    "tagListType": 3,
                    "list": [
                      10,
                      1,
                      13
                    ]
                  }
                },
                {
                  "tagType": 3,
                  "name": "state",
                  "value": 0
                }
              ]
            ]
          }
        },
        {
          "tagType": 9,
          "name": "palette",
          "value": {
            "tagListType": 10,
            "list": [
              [
                {
                  "tagType": 8,
                  "name": "Name",
                  "value": "minecraft:stone_bricks"
                }
              ],
              [
                {
                  "tagType": 10,
                  "name": "Properties",
                  "value": [
                    {
                      "tagType": 8,
                      "name": "type",
                      "value": "bottom"
                    }
                  ]
                },
                {
                  "tagType": 8,
                  "name": "Name",
                  "value": "minecraft:stone_brick_slab"
                }
              ],
              [
                {
                  "tagType": 10,
                  "name": "Properties",
                  "value": [
                    {
                      "tagType": 8,
                      "name": "type",
                      "value": "top"
                    }
                  ]
                },
                {
                  "tagType": 8,
                  "name": "Name",
                  "value": "minecraft:stone_brick_slab"
                }
              ],
              [
                {
                  "tagType": 10,
                  "name": "Properties",
                  "value": [
                    {
                      "tagType": 8,
                      "name": "facing",
                      "value": "south"
                    },
                    {
                      "tagType": 8,
                      "name": "half",
                      "value": "bottom"
                    },
                    {
                      "tagType": 8,
                      "name": "shape",
                      "value": "straight"
                    },
                    {
                      "tagType": 8,
                      "name": "waterlogged",
                      "value": "false"
                    }
                  ]
                },
                {
                  "tagType": 8,
                  "name": "Name",
                  "value": "minecraft:stone_brick_stairs"
                }
              ]
            ]
          }
        },
        {
          "tagType": 3,
          "name": "DataVersion",
          "value": 2215
        }
      ]
    }
  ]
}